django_payments_ecpay-1.0.2.dist-info/DESCRIPTION.rst
django_payments_ecpay-1.0.2.dist-info/METADATA
django_payments_ecpay-1.0.2.dist-info/RECORD
django_payments_ecpay-1.0.2.dist-info/WHEEL
django_payments_ecpay-1.0.2.dist-info/metadata.json
django_payments_ecpay-1.0.2.dist-info/top_level.txt
payments_ecpay/__init__.py
payments_ecpay/test_ecpay.py
