Metadata-Version: 2.0
Name: django-payments-ecpay
Version: 1.0.2
Summary: A django-payments backend for the ECPay (Taiwan) payment gateway.
Home-page: https://github.com/tornerdo/django-payments-ecpay
Author: Benjamin Xenos
Author-email: benjamin@tornerdo.com
License: MIT
Download-URL: https://github.com/tornerdo/django-payments-ecpay/archive/v1.0.tar.gz
Keywords: django-payments,payment gateway
Platform: UNKNOWN
